envfrom/__init__.py
envfrom/__main__.py
envfrom/envfrom.py
envfrom/plugins/__init__.py
envfrom/plugins/cli.py
envfrom/plugins/dir.py
envfrom/plugins/dotenv.py
envfrom/plugins/kube.py
envfrom/plugins/tools.py
envfrom/plugins/vault.py
envfrom-0.2.1.dist-info/LICENSE
envfrom-0.2.1.dist-info/METADATA
envfrom-0.2.1.dist-info/WHEEL
envfrom-0.2.1.dist-info/entry_points.txt
envfrom-0.2.1.dist-info/top_level.txt
envfrom-0.2.1.dist-info/RECORD
