Metadata-Version: 2.1
Name: envfrom
Version: 0.2.1
Summary: Call child process with custom environment
Home-page: http://github.com/rambobinator/envfrom
Author: rm_ass
Author-email: contact@romanmasse.com
License: MIT
Platform: UNKNOWN
Classifier: Intended Audience :: Developers
Classifier: Operating System :: OS Independent
Classifier: Programming Language :: Python
License-File: LICENSE
Requires-Dist: kubernetes (>=10.0.1)
Requires-Dist: requests (>=2.23.0)
Requires-Dist: nested-lookup (>=0.2.21)
Requires-Dist: hvac[parser] (>=0.10.5)
